{"directors": ["Federico Veiroj"], "rate": "", "cover_x": "", "star": "0", "title": "Beltomon", "url": "https://movie.douban.com/subject/30385278/", "casts": ["Gonzalo Delgado", "Olivia Molinaro Eijo", "Jeannette Sauksteliskis", "Tomás Wahrmann", "María Noel Gutiérrez"], "cover": "https://img3.doubanio.com/f/movie/30c6263b6db26d055cbbe73fe653e29014142ea3/pics/movie/movie_default_large.png", "id": "30385278", "cover_y": "", "type": "剧情 / 喜剧", "area": "乌拉圭 / 墨西哥 / 西班牙", "language": "西班牙语", "date": "2018-09-07(多伦多电影节)", "long": "74分钟", "votes": "0"}