{"directors": ["Miguel Ferrari"], "rate": "", "cover_x": "", "star": "0", "title": "La noche de las dos lunas", "url": "https://movie.douban.com/subject/30301454/", "casts": ["玛丽亚·巴兰科", "Luis Gerónimo Abreu", "Albi De Abreu", "Juan Jesús Valverde", "Nohely Arteaga"], "cover": "https://img3.doubanio.com/f/movie/30c6263b6db26d055cbbe73fe653e29014142ea3/pics/movie/movie_default_large.png", "id": "30301454", "cover_y": "", "type": "剧情", "area": "委内瑞拉 / 西班牙", "language": "西班牙语", "long": "117分钟", "votes": "0"}